Workbook

Sheet Inputs
A1: FINANCIAL MODEL INPUTS
A3: Business Information
A4: Business Name: | B4: Sarah's Online Bakery
A5: Planning Period: | B5: 12 Months
A7: Revenue Assumptions
A8: Product Name: | B8: Custom Cakes
A9: Price per Unit: | B9: 50
A10: Units Sold Month 1: | B10: 20
A11: Monthly Growth Rate: | B11: 0.1
A13: Expense Assumptions
A14: Ingredient Cost per Unit: | B14: 15
A15: Rent (monthly): | B15: 500
A16: Marketing (monthly): | B16: 200
A17: Utilities (monthly): | B17: 100
A18: Other Costs (monthly): | B18: 150

Sheet Calculations
A1: Month | B1: 1 | C1: 2 | D1: 3 | E1: 4 | F1: 5 | G1: 6 | H1: 7 | I1: 8 | J1: 9 | K1: 10 | L1: 11 | M1: 12
A3: Revenue
A4: Units Sold | B4: =Inputs!B10 -> 20 | C4: =B4*(1+Inputs!$B$11) -> 22 | D4: =C4*(1+Inputs!$B$11) -> 24.2 | E4: =D4*(1+Inputs!$B$11) -> 26.62 | F4: =E4*(1+Inputs!$B$11) -> 29.282 | G4: =F4*(1+Inputs!$B$11) -> 32.2102 | H4: =G4*(1+Inputs!$B$11) -> 35.43122 | I4: =H4*(1+Inputs!$B$11) -> 38.974342 | J4: =I4*(1+Inputs!$B$11) -> 42.871776 | ... M4: =L4*(1+Inputs!$B$11) -> 57.062334
A5: Price per Unit | B5: 50 | C5: =Inputs!$B$9 -> 50 | D5: =Inputs!$B$9 -> 50 | E5: =Inputs!$B$9 -> 50 | F5: =Inputs!$B$9 -> 50 | G5: =Inputs!$B$9 -> 50 | H5: =Inputs!$B$9 -> 50 | I5: =Inputs!$B$9 -> 50 | J5: =Inputs!$B$9 -> 50 | ... M5: =Inputs!$B$9 -> 50
A6: Total Revenue | B6: =B4*B5 -> 1000 | C6: =C4*C5 -> 1100 | D6: =D4*D5 -> 1210 | E6: =E4*E5 -> 1331 | F6: =F4*F5 -> 1464.1 | G6: =G4*G5 -> 1610.51 | H6: =H4*H5 -> 1771.561 | I6: =I4*I5 -> 1948.7171 | ... M6: =M4*M5 -> 2853.1167
A7: EXPENSES
A8: Cost of Goods | B8: =B4*Inputs!$B$14 -> 300 | C8: =C4*Inputs!$B$14 -> 330 | D8: =D4*Inputs!$B$14 -> 363 | E8: =E4*Inputs!$B$14 -> 399.3 | F8: =F4*Inputs!$B$14 -> 439.23 | G8: =G4*Inputs!$B$14 -> 483.153 | H8: =H4*Inputs!$B$14 -> 531.4683 | I8: =I4*Inputs!$B$14 -> 584.61513 | ... M8: =M4*Inputs!$B$14 -> 855.93501
A9: Rent | B9: =Inputs!$B$15 -> 500 | C9: =Inputs!$B$15 -> 500 | D9: =Inputs!$B$15 -> 500 | E9: =Inputs!$B$15 -> 500 | F9: =Inputs!$B$15 -> 500 | G9: =Inputs!$B$15 -> 500 | H9: =Inputs!$B$15 -> 500 | I9: =Inputs!$B$15 -> 500 | ... M9: =Inputs!$B$15 -> 500
A10: Marketing | B10: =Inputs!$B$16 -> 200 | C10: =Inputs!$B$16 -> 200 | D10: =Inputs!$B$16 -> 200 | E10: =Inputs!$B$16 -> 200 | F10: =Inputs!$B$16 -> 200 | G10: =Inputs!$B$16 -> 200 | H10: =Inputs!$B$16 -> 200 | I10: =Inputs!$B$16 -> 200 | ... M10: =Inputs!$B$16 -> 200
A11: Utilities | B11: =Inputs!$B$17 -> 100 | C11: =Inputs!$B$17 -> 100 | D11: =Inputs!$B$17 -> 100 | E11: =Inputs!$B$17 -> 100 | F11: =Inputs!$B$17 -> 100 | G11: =Inputs!$B$17 -> 100 | H11: =Inputs!$B$17 -> 100 | I11: =Inputs!$B$17 -> 100 | ... M11: =Inputs!$B$17 -> 100
A12: Other Costs | B12: =Inputs!$B$18 -> 150 | C12: =Inputs!$B$18 -> 150 | D12: =Inputs!$B$18 -> 150 | E12: =Inputs!$B$18 -> 150 | F12: =Inputs!$B$18 -> 150 | G12: =Inputs!$B$18 -> 150 | H12: =Inputs!$B$18 -> 150 | I12: =Inputs!$B$18 -> 150 | ... M12: =Inputs!$B$18 -> 150
A13: Total Expenses | B13: =SUM(B8:B12) -> 1250 | C13: =SUM(C8:C12) -> 1280 | D13: =SUM(D8:D12) -> 1313 | E13: =SUM(E8:E12) -> 1349.3 | F13: =SUM(F8:F12) -> 1389.23 | G13: =SUM(G8:G12) -> 1433.153 | H13: =SUM(H8:H12) -> 1481.4683 | I13: =SUM(I8:I12) -> 1534.6151 | ... M13: =SUM(M8:M12) -> 1805.935
A14: NET PROFIT | B14: =B6-B13 -> -250 | C14: =C6-C13 -> -180 | D14: =D6-D13 -> -103 | E14: =E6-E13 -> -18.3 | F14: =F6-F13 -> 74.87 | G14: =G6-G13 -> 177.357 | H14: =H6-H13 -> 290.0927 | I14: =I6-I13 -> 414.10197 | ... M14: =M6-M13 -> 1047.1817
A18: KEY METRICS
A19: Total Year Revenue: | B19: =SUM(B6:M6) -> 21384.284
A20: Total Year Expenses: | B20: =SUM(B14:M14) -> 3568.9986
A21: Net Profit/Loss: | B21: =B19-B20 -> 17815.285
A22: Profit Margin: | B22: =B21/B19 -> 0.83310179
A24: BREAK-EVEN ANALYSIS
A25: Cumulative Profit by Month: | B25: =B14 -> -250 | C25: =B25+C14 -> -430 | D25: =C25+D14 -> -533 | E25: =D25+E14 -> -551.3 | F25: =E25+F14 -> -476.43 | G25: =F25+G14 -> -299.073 | H25: =G25+H14 -> -8.9803 | I25: =H25+I14 -> 405.12167 | J25: =I25+J14 -> 955.63384 | ... M25: =L25+M14 -> 3568.9986

Sheet Dashboard
D3: FINANCIAL DASHBOARD
